{
  "$schema": "https://developer.microsoft.com/json-schemas/fabric/item/report/definition/visualContainer/2.1.0/schema.json",
  "name": "4dd31f846e99c48eb859",
  "position": {
    "x": 2.2197299994794486,
    "y": 154.17558382755308,
    "z": 5000,
    "height": 43.16916347171486,
    "width": 581.75586964263368,
    "tabOrder": 5000
  },
  "visual": {
    "visualType": "slicer",
    "query": {
      "queryState": {
        "Values": {
          "projections": [
            {
              "field": {
                "Column": {
                  "Expression": {
                    "SourceRef": {
                      "Entity": "Commodity"
                    }
                  },
                  "Property": "Row Labels"
                }
              },
              "queryRef": "Commodity.Row Labels",
              "nativeQueryRef": "Row Labels1",
              "active": true
            }
          ]
        }
      }
    },
    "objects": {
      "data": [
        {
          "properties": {
            "mode": {
              "expr": {
                "Literal": {
                  "Value": "'Basic'"
                }
              }
            }
          }
        }
      ],
      "general": [
        {
          "properties": {
            "orientation": {
              "expr": {
                "Literal": {
                  "Value": "1D"
                }
              }
            },
            "filter": {
              "filter": {
                "Version": 2,
                "From": [
                  {
                    "Name": "c",
                    "Entity": "Commodity",
                    "Type": 0
                  }
                ],
                "Where": [
                  {
                    "Condition": {
                      "In": {
                        "Expressions": [
                          {
                            "Column": {
                              "Expression": {
                                "SourceRef": {
                                  "Source": "c"
                                }
                              },
                              "Property": "Row Labels"
                            }
                          }
                        ],
                        "Values": [
                          [
                            {
                              "Literal": {
                                "Value": "'Imports'"
                              }
                            }
                          ]
                        ]
                      }
                    }
                  }
                ]
              }
            }
          }
        }
      ],
      "header": [
        {
          "properties": {
            "show": {
              "expr": {
                "Literal": {
                  "Value": "false"
                }
              }
            }
          }
        }
      ],
      "selection": [
        {
          "properties": {
            "strictSingleSelect": {
              "expr": {
                "Literal": {
                  "Value": "false"
                }
              }
            }
          }
        }
      ]
    },
    "drillFilterOtherVisuals": true
  }
}